traja/__init__.py
traja/accessor.py
traja/core.py
traja/frame.py
traja/parsers.py
traja/plotting.py
traja/trajectory.py
traja/contrib/__init__.py
traja/contrib/rdp.py
traja/dataset/__init__.py
traja/dataset/dataset.py
traja/dataset/example.py
traja/dataset/generator.py
traja/dataset/pedestrian.py
traja/models/__init__.py
traja/models/inference.py
traja/models/losses.py
traja/models/manifold.py
traja/models/optimizers.py
traja/models/train.py
traja/models/utils.py
traja/models/base_models/MLPClassifier.py
traja/models/base_models/MLPRegressor.py
traja/models/base_models/__init__.py
traja/models/generative_models/__init__.py
traja/models/generative_models/vae.py
traja/models/generative_models/vaegan.py
traja/models/predictive_models/__init__.py
traja/models/predictive_models/ae.py
traja/models/predictive_models/lstm.py
traja/stats/brownian.py
traja/tests/.gitignore
traja/tests/__init__.py
traja/tests/test_accessor.py
traja/tests/test_dataset.py
traja/tests/test_losses.py
traja/tests/test_models.py
traja/tests/test_optimizers.py
traja/tests/test_parsers.py
traja/tests/test_plotting.py
traja/tests/test_stats.py
traja/tests/test_trajadataframe.py
traja/tests/test_trajectory.py
traja/tests/data/3527.csv
traja-25.0.1.dist-info/licenses/LICENSE
traja-25.0.1.dist-info/METADATA
traja-25.0.1.dist-info/WHEEL
traja-25.0.1.dist-info/top_level.txt
traja-25.0.1.dist-info/RECORD
