Metadata-Version: 2.4
Name: traja
Version: 25.0.1
Summary: Traja is a trajectory analysis and visualization tool
Home-page: https://github.com/traja-team/traja
Author: Justin Shenk
Author-email: Justin Shenk <shenkjustin@gmail.com>
License: MIT
Project-URL: Homepage, https://github.com/traja-team/traja
Project-URL: Documentation, https://traja.rtfd.io/en/latest/
Project-URL: Bug Tracker, https://github.com/traja-team/traja/issues
Project-URL: Source Code, https://github.com/traja-team/traja
Keywords: trajectory,analysis,animal tracking,movement ecology
Classifier: Development Status :: 5 - Production/Stable
Classifier: Intended Audience :: Developers
Classifier: Intended Audience :: Education
Classifier: Intended Audience :: Science/Research
Classifier: License :: OSI Approved :: MIT License
Classifier: Programming Language :: Python :: 3
Classifier: Programming Language :: Python :: 3.8
Classifier: Programming Language :: Python :: 3.9
Classifier: Programming Language :: Python :: 3.10
Classifier: Programming Language :: Python :: 3.11
Classifier: Programming Language :: Python :: 3.12
Classifier: Topic :: Scientific/Engineering :: Mathematics
Classifier: Topic :: Software Development :: Libraries :: Python Modules
Classifier: Topic :: Software Development :: Libraries
Requires-Python: >= 3.8
License-File: LICENSE
Requires-Dist: matplotlib>=3.3.0
Requires-Dist: pandas>=1.2.0
Requires-Dist: numpy>=1.22.0
Requires-Dist: shapely>=1.7.0
Requires-Dist: scipy>=1.4.1
Requires-Dist: tzlocal>=2.0.0
Provides-Extra: all
Requires-Dist: torch>=1.7.0; extra == "all"
Requires-Dist: fastdtw>=0.3.0; extra == "all"
Provides-Extra: dev
Requires-Dist: pytest>=6.0.0; extra == "dev"
Requires-Dist: pytest-cov>=2.10.0; extra == "dev"
Requires-Dist: flake8>=3.8.0; extra == "dev"
Requires-Dist: black>=22.0.0; extra == "dev"
Requires-Dist: isort>=5.0.0; extra == "dev"
Requires-Dist: mypy>=0.950; extra == "dev"
Requires-Dist: pre-commit>=2.15.0; extra == "dev"
Provides-Extra: docs
Requires-Dist: sphinx>=4.0.0; extra == "docs"
Requires-Dist: sphinx-rtd-theme>=0.5.0; extra == "docs"
Requires-Dist: numpydoc>=1.1.0; extra == "docs"
Dynamic: author
Dynamic: home-page
Dynamic: license-file
Dynamic: requires-python
